setup.py
sunnyday/__init__.py
sunnyday/sunnyday.py
yet_another_sunnyday.egg-info/PKG-INFO
yet_another_sunnyday.egg-info/SOURCES.txt
yet_another_sunnyday.egg-info/dependency_links.txt
yet_another_sunnyday.egg-info/requires.txt
yet_another_sunnyday.egg-info/top_level.txt