Metadata-Version: 2.1
Name: yet-another-sunnyday
Version: 2.0.0
Summary: Weather forecast data
Home-page: https://github.com/dbetm/crash-course-python/tree/master/advanced_python_oop_udemy_course/app_11_weather_client_package/sunnyday
Author: David Betancourt
Author-email: davbetm@gmail.com
License: MIT
Keywords: weather,forecast,openweather
Platform: UNKNOWN
Classifier: Development Status :: 3 - Alpha
Classifier: Intended Audience :: Developers
Classifier: Topic :: Software Development :: Build Tools
Classifier: License :: OSI Approved :: MIT License
Classifier: Programming Language :: Python :: 3.8
Classifier: Programming Language :: Python :: 3.9
